[
    {
        "Resolution": {
            "Height": 720,
            "Width": 1280
        },
        "Rate": 20024,
        "VmafScore": 98.333891
    },
    {
        "Resolution": {
            "Height": 720,
            "Width": 1280
        },
        "Rate": 18978,
        "VmafScore": 98.273167
    },
    {
        "Resolution": {
            "Height": 720,
            "Width": 1280
        },
        "Rate": 17932,
        "VmafScore": 98.210585
    },
    {
        "Resolution": {
            "Height": 720,
            "Width": 1280
        },
        "Rate": 16886,
        "VmafScore": 98.130441
    },
    {
        "Resolution": {
            "Height": 720,
            "Width": 1280
        },
        "Rate": 15840,
        "VmafScore": 98.023656
    },
    {
        "Resolution": {
            "Height": 720,
            "Width": 1280
        },
        "Rate": 14794,
        "VmafScore": 97.911534
    },
    {
        "Resolution": {
            "Height": 720,
            "Width": 1280
        },
        "Rate": 13748,
        "VmafScore": 97.781443
    },
    {
        "Resolution": {
            "Height": 720,
            "Width": 1280
        },
        "Rate": 12702,
        "VmafScore": 97.630114
    },
    {
        "Resolution": {
            "Height": 720,
            "Width": 1280
        },
        "Rate": 11656,
        "VmafScore": 97.443082
    },
    {
        "Resolution": {
            "Height": 720,
            "Width": 1280
        },
        "Rate": 10610,
        "VmafScore": 97.207865
    },
    {
        "Resolution": {
            "Height": 720,
            "Width": 1280
        },
        "Rate": 9564,
        "VmafScore": 96.9447
    },
    {
        "Resolution": {
            "Height": 720,
            "Width": 1280
        },
        "Rate": 8518,
        "VmafScore": 96.642434
    },
    {
        "Resolution": {
            "Height": 720,
            "Width": 1280
        },
        "Rate": 7472,
        "VmafScore": 96.213064
    },
    {
        "Resolution": {
            "Height": 720,
            "Width": 1280
        },
        "Rate": 6426,
        "VmafScore": 95.770043
    },
    {
        "Resolution": {
            "Height": 720,
            "Width": 1280
        },
        "Rate": 5380,
        "VmafScore": 95.268249
    },
    {
        "Resolution": {
            "Height": 720,
            "Width": 1280
        },
        "Rate": 4334,
        "VmafScore": 94.582599
    },
    {
        "Resolution": {
            "Height": 720,
            "Width": 1280
        },
        "Rate": 3288,
        "VmafScore": 93.71758
    },
    {
        "Resolution": {
            "Height": 720,
            "Width": 1280
        },
        "Rate": 2242,
        "VmafScore": 92.30542
    },
    {
        "Resolution": {
            "Height": 720,
            "Width": 1280
        },
        "Rate": 1196,
        "VmafScore": 88.721877
    },
    {
        "Resolution": {
            "Height": 540,
            "Width": 960
        },
        "Rate": 150,
        "VmafScore": 48.770925
    }
]
