[
    {
        "Resolution": {
            "Height": 720,
            "Width": 1280
        },
        "Rate": 4900,
        "VmafScore": 97.39139
    },
    {
        "Resolution": {
            "Height": 720,
            "Width": 1280
        },
        "Rate": 4650,
        "VmafScore": 97.31275
    },
    {
        "Resolution": {
            "Height": 720,
            "Width": 1280
        },
        "Rate": 4400,
        "VmafScore": 97.242693
    },
    {
        "Resolution": {
            "Height": 720,
            "Width": 1280
        },
        "Rate": 4150,
        "VmafScore": 97.153288
    },
    {
        "Resolution": {
            "Height": 720,
            "Width": 1280
        },
        "Rate": 3900,
        "VmafScore": 97.063935
    },
    {
        "Resolution": {
            "Height": 720,
            "Width": 1280
        },
        "Rate": 3650,
        "VmafScore": 96.9562
    },
    {
        "Resolution": {
            "Height": 720,
            "Width": 1280
        },
        "Rate": 3400,
        "VmafScore": 96.822924
    },
    {
        "Resolution": {
            "Height": 720,
            "Width": 1280
        },
        "Rate": 3150,
        "VmafScore": 96.674148
    },
    {
        "Resolution": {
            "Height": 720,
            "Width": 1280
        },
        "Rate": 2900,
        "VmafScore": 96.5174
    },
    {
        "Resolution": {
            "Height": 720,
            "Width": 1280
        },
        "Rate": 2650,
        "VmafScore": 96.305293
    },
    {
        "Resolution": {
            "Height": 720,
            "Width": 1280
        },
        "Rate": 2400,
        "VmafScore": 96.093388
    },
    {
        "Resolution": {
            "Height": 720,
            "Width": 1280
        },
        "Rate": 2150,
        "VmafScore": 95.83558
    },
    {
        "Resolution": {
            "Height": 720,
            "Width": 1280
        },
        "Rate": 1900,
        "VmafScore": 95.528462
    },
    {
        "Resolution": {
            "Height": 720,
            "Width": 1280
        },
        "Rate": 1650,
        "VmafScore": 95.181517
    },
    {
        "Resolution": {
            "Height": 720,
            "Width": 1280
        },
        "Rate": 1400,
        "VmafScore": 94.736496
    },
    {
        "Resolution": {
            "Height": 720,
            "Width": 1280
        },
        "Rate": 1150,
        "VmafScore": 94.1316
    },
    {
        "Resolution": {
            "Height": 720,
            "Width": 1280
        },
        "Rate": 900,
        "VmafScore": 93.210235
    },
    {
        "Resolution": {
            "Height": 720,
            "Width": 1280
        },
        "Rate": 650,
        "VmafScore": 91.798405
    },
    {
        "Resolution": {
            "Height": 720,
            "Width": 1280
        },
        "Rate": 400,
        "VmafScore": 88.911117
    },
    {
        "Resolution": {
            "Height": 720,
            "Width": 1280
        },
        "Rate": 150,
        "VmafScore": 78.051499
    }
]
