[
    {
        "Resolution": {
            "Height": 480,
            "Width": 640
        },
        "Rate": 24299,
        "VmafScore": 99.902438
    },
    {
        "Resolution": {
            "Height": 480,
            "Width": 640
        },
        "Rate": 23028,
        "VmafScore": 99.897237
    },
    {
        "Resolution": {
            "Height": 480,
            "Width": 640
        },
        "Rate": 21757,
        "VmafScore": 99.89352
    },
    {
        "Resolution": {
            "Height": 480,
            "Width": 640
        },
        "Rate": 20486,
        "VmafScore": 99.886684
    },
    {
        "Resolution": {
            "Height": 480,
            "Width": 640
        },
        "Rate": 19215,
        "VmafScore": 99.881445
    },
    {
        "Resolution": {
            "Height": 480,
            "Width": 640
        },
        "Rate": 17944,
        "VmafScore": 99.874109
    },
    {
        "Resolution": {
            "Height": 480,
            "Width": 640
        },
        "Rate": 16673,
        "VmafScore": 99.866051
    },
    {
        "Resolution": {
            "Height": 480,
            "Width": 640
        },
        "Rate": 15402,
        "VmafScore": 99.854536
    },
    {
        "Resolution": {
            "Height": 480,
            "Width": 640
        },
        "Rate": 14131,
        "VmafScore": 99.840268
    },
    {
        "Resolution": {
            "Height": 480,
            "Width": 640
        },
        "Rate": 12860,
        "VmafScore": 99.817831
    },
    {
        "Resolution": {
            "Height": 480,
            "Width": 640
        },
        "Rate": 11589,
        "VmafScore": 99.788539
    },
    {
        "Resolution": {
            "Height": 480,
            "Width": 640
        },
        "Rate": 10318,
        "VmafScore": 99.732886
    },
    {
        "Resolution": {
            "Height": 480,
            "Width": 640
        },
        "Rate": 9047,
        "VmafScore": 99.606899
    },
    {
        "Resolution": {
            "Height": 480,
            "Width": 640
        },
        "Rate": 7776,
        "VmafScore": 99.27927
    },
    {
        "Resolution": {
            "Height": 480,
            "Width": 640
        },
        "Rate": 6505,
        "VmafScore": 98.498029
    },
    {
        "Resolution": {
            "Height": 480,
            "Width": 640
        },
        "Rate": 5234,
        "VmafScore": 96.922978
    },
    {
        "Resolution": {
            "Height": 480,
            "Width": 640
        },
        "Rate": 3963,
        "VmafScore": 93.76719
    },
    {
        "Resolution": {
            "Height": 360,
            "Width": 640
        },
        "Rate": 2692,
        "VmafScore": 87.974549
    },
    {
        "Resolution": {
            "Height": 270,
            "Width": 480
        },
        "Rate": 1421,
        "VmafScore": 77.845448
    },
    {
        "Resolution": {
            "Height": 270,
            "Width": 480
        },
        "Rate": 150,
        "VmafScore": -1
    }
]
