[
    {
        "Resolution": {
            "Height": 480,
            "Width": 640
        },
        "Rate": 4273,
        "VmafScore": 97.025297
    },
    {
        "Resolution": {
            "Height": 480,
            "Width": 640
        },
        "Rate": 4056,
        "VmafScore": 96.851817
    },
    {
        "Resolution": {
            "Height": 480,
            "Width": 640
        },
        "Rate": 3839,
        "VmafScore": 96.669906
    },
    {
        "Resolution": {
            "Height": 480,
            "Width": 640
        },
        "Rate": 3622,
        "VmafScore": 96.471726
    },
    {
        "Resolution": {
            "Height": 480,
            "Width": 640
        },
        "Rate": 3405,
        "VmafScore": 96.24249
    },
    {
        "Resolution": {
            "Height": 480,
            "Width": 640
        },
        "Rate": 3188,
        "VmafScore": 95.977035
    },
    {
        "Resolution": {
            "Height": 480,
            "Width": 640
        },
        "Rate": 2971,
        "VmafScore": 95.693331
    },
    {
        "Resolution": {
            "Height": 480,
            "Width": 640
        },
        "Rate": 2754,
        "VmafScore": 95.349964
    },
    {
        "Resolution": {
            "Height": 480,
            "Width": 640
        },
        "Rate": 2537,
        "VmafScore": 94.970613
    },
    {
        "Resolution": {
            "Height": 480,
            "Width": 640
        },
        "Rate": 2320,
        "VmafScore": 94.524696
    },
    {
        "Resolution": {
            "Height": 480,
            "Width": 640
        },
        "Rate": 2103,
        "VmafScore": 94.000637
    },
    {
        "Resolution": {
            "Height": 480,
            "Width": 640
        },
        "Rate": 1886,
        "VmafScore": 93.449858
    },
    {
        "Resolution": {
            "Height": 480,
            "Width": 640
        },
        "Rate": 1669,
        "VmafScore": 92.80452
    },
    {
        "Resolution": {
            "Height": 480,
            "Width": 640
        },
        "Rate": 1452,
        "VmafScore": 92.059059
    },
    {
        "Resolution": {
            "Height": 480,
            "Width": 640
        },
        "Rate": 1235,
        "VmafScore": 91.243037
    },
    {
        "Resolution": {
            "Height": 480,
            "Width": 640
        },
        "Rate": 1018,
        "VmafScore": 90.262146
    },
    {
        "Resolution": {
            "Height": 480,
            "Width": 640
        },
        "Rate": 801,
        "VmafScore": 89.004922
    },
    {
        "Resolution": {
            "Height": 480,
            "Width": 640
        },
        "Rate": 584,
        "VmafScore": 87.320174
    },
    {
        "Resolution": {
            "Height": 480,
            "Width": 640
        },
        "Rate": 367,
        "VmafScore": 84.452328
    },
    {
        "Resolution": {
            "Height": 360,
            "Width": 640
        },
        "Rate": 150,
        "VmafScore": 76.303034
    }
]
