[
    {
        "Resolution": {
            "Height": 720,
            "Width": 1280
        },
        "Rate": 25154,
        "VmafScore": 98.661925
    },
    {
        "Resolution": {
            "Height": 720,
            "Width": 1280
        },
        "Rate": 23838,
        "VmafScore": 98.49225
    },
    {
        "Resolution": {
            "Height": 720,
            "Width": 1280
        },
        "Rate": 22522,
        "VmafScore": 98.290614
    },
    {
        "Resolution": {
            "Height": 720,
            "Width": 1280
        },
        "Rate": 21206,
        "VmafScore": 98.02881
    },
    {
        "Resolution": {
            "Height": 720,
            "Width": 1280
        },
        "Rate": 19890,
        "VmafScore": 97.736658
    },
    {
        "Resolution": {
            "Height": 720,
            "Width": 1280
        },
        "Rate": 18574,
        "VmafScore": 97.380033
    },
    {
        "Resolution": {
            "Height": 720,
            "Width": 1280
        },
        "Rate": 17258,
        "VmafScore": 96.985717
    },
    {
        "Resolution": {
            "Height": 720,
            "Width": 1280
        },
        "Rate": 15942,
        "VmafScore": 96.524443
    },
    {
        "Resolution": {
            "Height": 720,
            "Width": 1280
        },
        "Rate": 14626,
        "VmafScore": 96.017007
    },
    {
        "Resolution": {
            "Height": 720,
            "Width": 1280
        },
        "Rate": 13310,
        "VmafScore": 95.444611
    },
    {
        "Resolution": {
            "Height": 720,
            "Width": 1280
        },
        "Rate": 11994,
        "VmafScore": 94.752761
    },
    {
        "Resolution": {
            "Height": 720,
            "Width": 1280
        },
        "Rate": 10678,
        "VmafScore": 93.948521
    },
    {
        "Resolution": {
            "Height": 720,
            "Width": 1280
        },
        "Rate": 9362,
        "VmafScore": 93.051074
    },
    {
        "Resolution": {
            "Height": 720,
            "Width": 1280
        },
        "Rate": 8046,
        "VmafScore": 91.883226
    },
    {
        "Resolution": {
            "Height": 720,
            "Width": 1280
        },
        "Rate": 6730,
        "VmafScore": 90.356353
    },
    {
        "Resolution": {
            "Height": 540,
            "Width": 960
        },
        "Rate": 5414,
        "VmafScore": 88.637249
    },
    {
        "Resolution": {
            "Height": 540,
            "Width": 960
        },
        "Rate": 4098,
        "VmafScore": 86.95399
    },
    {
        "Resolution": {
            "Height": 540,
            "Width": 960
        },
        "Rate": 2782,
        "VmafScore": 84.485181
    },
    {
        "Resolution": {
            "Height": 540,
            "Width": 960
        },
        "Rate": 1466,
        "VmafScore": 79.59699
    },
    {
        "Resolution": {
            "Height": 360,
            "Width": 640
        },
        "Rate": 150,
        "VmafScore": 49.941505
    }
]
