[
    {
        "Resolution": {
            "Height": 480,
            "Width": 640
        },
        "Rate": 5527,
        "VmafScore": 98.06425
    },
    {
        "Resolution": {
            "Height": 480,
            "Width": 640
        },
        "Rate": 5244,
        "VmafScore": 97.996855
    },
    {
        "Resolution": {
            "Height": 480,
            "Width": 640
        },
        "Rate": 4961,
        "VmafScore": 97.920682
    },
    {
        "Resolution": {
            "Height": 480,
            "Width": 640
        },
        "Rate": 4678,
        "VmafScore": 97.846245
    },
    {
        "Resolution": {
            "Height": 480,
            "Width": 640
        },
        "Rate": 4395,
        "VmafScore": 97.765969
    },
    {
        "Resolution": {
            "Height": 480,
            "Width": 640
        },
        "Rate": 4112,
        "VmafScore": 97.677066
    },
    {
        "Resolution": {
            "Height": 480,
            "Width": 640
        },
        "Rate": 3829,
        "VmafScore": 97.56759
    },
    {
        "Resolution": {
            "Height": 480,
            "Width": 640
        },
        "Rate": 3546,
        "VmafScore": 97.447876
    },
    {
        "Resolution": {
            "Height": 480,
            "Width": 640
        },
        "Rate": 3263,
        "VmafScore": 97.294852
    },
    {
        "Resolution": {
            "Height": 480,
            "Width": 640
        },
        "Rate": 2980,
        "VmafScore": 97.11719
    },
    {
        "Resolution": {
            "Height": 480,
            "Width": 640
        },
        "Rate": 2697,
        "VmafScore": 96.925984
    },
    {
        "Resolution": {
            "Height": 480,
            "Width": 640
        },
        "Rate": 2414,
        "VmafScore": 96.677197
    },
    {
        "Resolution": {
            "Height": 480,
            "Width": 640
        },
        "Rate": 2131,
        "VmafScore": 96.354105
    },
    {
        "Resolution": {
            "Height": 480,
            "Width": 640
        },
        "Rate": 1848,
        "VmafScore": 95.974129
    },
    {
        "Resolution": {
            "Height": 480,
            "Width": 640
        },
        "Rate": 1565,
        "VmafScore": 95.463085
    },
    {
        "Resolution": {
            "Height": 480,
            "Width": 640
        },
        "Rate": 1282,
        "VmafScore": 94.761855
    },
    {
        "Resolution": {
            "Height": 480,
            "Width": 640
        },
        "Rate": 999,
        "VmafScore": 93.631749
    },
    {
        "Resolution": {
            "Height": 480,
            "Width": 640
        },
        "Rate": 716,
        "VmafScore": 91.718235
    },
    {
        "Resolution": {
            "Height": 360,
            "Width": 640
        },
        "Rate": 433,
        "VmafScore": 87.518994
    },
    {
        "Resolution": {
            "Height": 270,
            "Width": 480
        },
        "Rate": 150,
        "VmafScore": 70.010368
    }
]
