[
    {
        "Resolution": {
            "Height": 480,
            "Width": 854
        },
        "Rate": 3513,
        "VmafScore": 98.799251
    },
    {
        "Resolution": {
            "Height": 480,
            "Width": 854
        },
        "Rate": 3336,
        "VmafScore": 98.768141
    },
    {
        "Resolution": {
            "Height": 480,
            "Width": 854
        },
        "Rate": 3159,
        "VmafScore": 98.746527
    },
    {
        "Resolution": {
            "Height": 480,
            "Width": 854
        },
        "Rate": 2982,
        "VmafScore": 98.734203
    },
    {
        "Resolution": {
            "Height": 480,
            "Width": 854
        },
        "Rate": 2805,
        "VmafScore": 98.682788
    },
    {
        "Resolution": {
            "Height": 480,
            "Width": 854
        },
        "Rate": 2628,
        "VmafScore": 98.635791
    },
    {
        "Resolution": {
            "Height": 480,
            "Width": 854
        },
        "Rate": 2451,
        "VmafScore": 98.574787
    },
    {
        "Resolution": {
            "Height": 480,
            "Width": 854
        },
        "Rate": 2274,
        "VmafScore": 98.490883
    },
    {
        "Resolution": {
            "Height": 480,
            "Width": 854
        },
        "Rate": 2097,
        "VmafScore": 98.424666
    },
    {
        "Resolution": {
            "Height": 480,
            "Width": 854
        },
        "Rate": 1920,
        "VmafScore": 98.338904
    },
    {
        "Resolution": {
            "Height": 480,
            "Width": 854
        },
        "Rate": 1743,
        "VmafScore": 98.21461
    },
    {
        "Resolution": {
            "Height": 480,
            "Width": 854
        },
        "Rate": 1566,
        "VmafScore": 98.101302
    },
    {
        "Resolution": {
            "Height": 480,
            "Width": 854
        },
        "Rate": 1389,
        "VmafScore": 97.969475
    },
    {
        "Resolution": {
            "Height": 480,
            "Width": 854
        },
        "Rate": 1212,
        "VmafScore": 97.731289
    },
    {
        "Resolution": {
            "Height": 480,
            "Width": 854
        },
        "Rate": 1035,
        "VmafScore": 97.367614
    },
    {
        "Resolution": {
            "Height": 480,
            "Width": 854
        },
        "Rate": 858,
        "VmafScore": 96.9138
    },
    {
        "Resolution": {
            "Height": 480,
            "Width": 854
        },
        "Rate": 681,
        "VmafScore": 96.113856
    },
    {
        "Resolution": {
            "Height": 480,
            "Width": 854
        },
        "Rate": 504,
        "VmafScore": 94.443974
    },
    {
        "Resolution": {
            "Height": 480,
            "Width": 854
        },
        "Rate": 327,
        "VmafScore": 90.477288
    },
    {
        "Resolution": {
            "Height": 360,
            "Width": 640
        },
        "Rate": 150,
        "VmafScore": 76.647918
    }
]
