[
    {
        "Resolution": {
            "Height": 720,
            "Width": 1280
        },
        "Rate": 26522,
        "VmafScore": 99.475107
    },
    {
        "Resolution": {
            "Height": 720,
            "Width": 1280
        },
        "Rate": 25134,
        "VmafScore": 99.397448
    },
    {
        "Resolution": {
            "Height": 720,
            "Width": 1280
        },
        "Rate": 23746,
        "VmafScore": 99.313795
    },
    {
        "Resolution": {
            "Height": 720,
            "Width": 1280
        },
        "Rate": 22358,
        "VmafScore": 99.217459
    },
    {
        "Resolution": {
            "Height": 720,
            "Width": 1280
        },
        "Rate": 20970,
        "VmafScore": 99.112539
    },
    {
        "Resolution": {
            "Height": 720,
            "Width": 1280
        },
        "Rate": 19582,
        "VmafScore": 98.990045
    },
    {
        "Resolution": {
            "Height": 720,
            "Width": 1280
        },
        "Rate": 18194,
        "VmafScore": 98.843341
    },
    {
        "Resolution": {
            "Height": 720,
            "Width": 1280
        },
        "Rate": 16806,
        "VmafScore": 98.673076
    },
    {
        "Resolution": {
            "Height": 720,
            "Width": 1280
        },
        "Rate": 15418,
        "VmafScore": 98.468773
    },
    {
        "Resolution": {
            "Height": 720,
            "Width": 1280
        },
        "Rate": 14030,
        "VmafScore": 98.230999
    },
    {
        "Resolution": {
            "Height": 720,
            "Width": 1280
        },
        "Rate": 12642,
        "VmafScore": 97.933619
    },
    {
        "Resolution": {
            "Height": 720,
            "Width": 1280
        },
        "Rate": 11254,
        "VmafScore": 97.567787
    },
    {
        "Resolution": {
            "Height": 720,
            "Width": 1280
        },
        "Rate": 9866,
        "VmafScore": 97.110558
    },
    {
        "Resolution": {
            "Height": 720,
            "Width": 1280
        },
        "Rate": 8478,
        "VmafScore": 96.569278
    },
    {
        "Resolution": {
            "Height": 720,
            "Width": 1280
        },
        "Rate": 7090,
        "VmafScore": 95.916531
    },
    {
        "Resolution": {
            "Height": 720,
            "Width": 1280
        },
        "Rate": 5702,
        "VmafScore": 95.097534
    },
    {
        "Resolution": {
            "Height": 720,
            "Width": 1280
        },
        "Rate": 4314,
        "VmafScore": 94.035501
    },
    {
        "Resolution": {
            "Height": 720,
            "Width": 1280
        },
        "Rate": 2926,
        "VmafScore": 92.547685
    },
    {
        "Resolution": {
            "Height": 720,
            "Width": 1280
        },
        "Rate": 1538,
        "VmafScore": 89.625856
    },
    {
        "Resolution": {
            "Height": 540,
            "Width": 960
        },
        "Rate": 150,
        "VmafScore": 53.650695
    }
]
