[
    {
        "Resolution": {
            "Height": 1080,
            "Width": 1920
        },
        "Rate": 104384,
        "VmafScore": 98.867969
    },
    {
        "Resolution": {
            "Height": 1080,
            "Width": 1920
        },
        "Rate": 98898,
        "VmafScore": 98.813353
    },
    {
        "Resolution": {
            "Height": 1080,
            "Width": 1920
        },
        "Rate": 93412,
        "VmafScore": 98.746344
    },
    {
        "Resolution": {
            "Height": 1080,
            "Width": 1920
        },
        "Rate": 87926,
        "VmafScore": 98.671942
    },
    {
        "Resolution": {
            "Height": 1080,
            "Width": 1920
        },
        "Rate": 82440,
        "VmafScore": 98.590099
    },
    {
        "Resolution": {
            "Height": 1080,
            "Width": 1920
        },
        "Rate": 76954,
        "VmafScore": 98.50289
    },
    {
        "Resolution": {
            "Height": 1080,
            "Width": 1920
        },
        "Rate": 71468,
        "VmafScore": 98.40729
    },
    {
        "Resolution": {
            "Height": 1080,
            "Width": 1920
        },
        "Rate": 65982,
        "VmafScore": 98.291024
    },
    {
        "Resolution": {
            "Height": 1080,
            "Width": 1920
        },
        "Rate": 60496,
        "VmafScore": 98.163526
    },
    {
        "Resolution": {
            "Height": 1080,
            "Width": 1920
        },
        "Rate": 55010,
        "VmafScore": 98.005857
    },
    {
        "Resolution": {
            "Height": 1080,
            "Width": 1920
        },
        "Rate": 49524,
        "VmafScore": 97.798479
    },
    {
        "Resolution": {
            "Height": 1080,
            "Width": 1920
        },
        "Rate": 44038,
        "VmafScore": 97.524584
    },
    {
        "Resolution": {
            "Height": 1080,
            "Width": 1920
        },
        "Rate": 38552,
        "VmafScore": 97.14595
    },
    {
        "Resolution": {
            "Height": 1080,
            "Width": 1920
        },
        "Rate": 33066,
        "VmafScore": 96.581433
    },
    {
        "Resolution": {
            "Height": 1080,
            "Width": 1920
        },
        "Rate": 27580,
        "VmafScore": 95.503974
    },
    {
        "Resolution": {
            "Height": 1080,
            "Width": 1920
        },
        "Rate": 22094,
        "VmafScore": 93.242431
    },
    {
        "Resolution": {
            "Height": 1080,
            "Width": 1920
        },
        "Rate": 16608,
        "VmafScore": 89.258444
    },
    {
        "Resolution": {
            "Height": 720,
            "Width": 1280
        },
        "Rate": 11122,
        "VmafScore": 83.079887
    },
    {
        "Resolution": {
            "Height": 720,
            "Width": 1280
        },
        "Rate": 5636,
        "VmafScore": 75.144559
    },
    {
        "Resolution": {
            "Height": 540,
            "Width": 960
        },
        "Rate": 150,
        "VmafScore": 10.67711
    }
]
