[
    {
        "Resolution": {
            "Height": 1080,
            "Width": 1440
        },
        "Rate": 42330,
        "VmafScore": 97.790777
    },
    {
        "Resolution": {
            "Height": 1080,
            "Width": 1440
        },
        "Rate": 40110,
        "VmafScore": 97.712588
    },
    {
        "Resolution": {
            "Height": 1080,
            "Width": 1440
        },
        "Rate": 37890,
        "VmafScore": 97.615895
    },
    {
        "Resolution": {
            "Height": 1080,
            "Width": 1440
        },
        "Rate": 35670,
        "VmafScore": 97.494899
    },
    {
        "Resolution": {
            "Height": 1080,
            "Width": 1440
        },
        "Rate": 33450,
        "VmafScore": 97.356942
    },
    {
        "Resolution": {
            "Height": 1080,
            "Width": 1440
        },
        "Rate": 31230,
        "VmafScore": 97.204061
    },
    {
        "Resolution": {
            "Height": 1080,
            "Width": 1440
        },
        "Rate": 29010,
        "VmafScore": 97.030976
    },
    {
        "Resolution": {
            "Height": 1080,
            "Width": 1440
        },
        "Rate": 26790,
        "VmafScore": 96.840258
    },
    {
        "Resolution": {
            "Height": 1080,
            "Width": 1440
        },
        "Rate": 24570,
        "VmafScore": 96.608277
    },
    {
        "Resolution": {
            "Height": 1080,
            "Width": 1440
        },
        "Rate": 22350,
        "VmafScore": 96.34042
    },
    {
        "Resolution": {
            "Height": 1080,
            "Width": 1440
        },
        "Rate": 20130,
        "VmafScore": 96.013355
    },
    {
        "Resolution": {
            "Height": 1080,
            "Width": 1440
        },
        "Rate": 17910,
        "VmafScore": 95.634206
    },
    {
        "Resolution": {
            "Height": 1080,
            "Width": 1440
        },
        "Rate": 15690,
        "VmafScore": 95.179286
    },
    {
        "Resolution": {
            "Height": 1080,
            "Width": 1440
        },
        "Rate": 13470,
        "VmafScore": 94.628769
    },
    {
        "Resolution": {
            "Height": 1080,
            "Width": 1440
        },
        "Rate": 11250,
        "VmafScore": 93.932053
    },
    {
        "Resolution": {
            "Height": 1080,
            "Width": 1440
        },
        "Rate": 9030,
        "VmafScore": 93.020852
    },
    {
        "Resolution": {
            "Height": 1080,
            "Width": 1440
        },
        "Rate": 6810,
        "VmafScore": 91.75256
    },
    {
        "Resolution": {
            "Height": 1080,
            "Width": 1440
        },
        "Rate": 4590,
        "VmafScore": 89.76783
    },
    {
        "Resolution": {
            "Height": 1080,
            "Width": 1440
        },
        "Rate": 2370,
        "VmafScore": 85.652603
    },
    {
        "Resolution": {
            "Height": 720,
            "Width": 1280
        },
        "Rate": 150,
        "VmafScore": 31.769521
    }
]
