[
    {
        "Resolution": {
            "Height": 1080,
            "Width": 1920
        },
        "Rate": 27434,
        "VmafScore": 96.782372
    },
    {
        "Resolution": {
            "Height": 1080,
            "Width": 1920
        },
        "Rate": 25998,
        "VmafScore": 96.796181
    },
    {
        "Resolution": {
            "Height": 1080,
            "Width": 1920
        },
        "Rate": 24562,
        "VmafScore": 96.48725
    },
    {
        "Resolution": {
            "Height": 1080,
            "Width": 1920
        },
        "Rate": 23126,
        "VmafScore": 96.256793
    },
    {
        "Resolution": {
            "Height": 1080,
            "Width": 1920
        },
        "Rate": 21690,
        "VmafScore": 96.013049
    },
    {
        "Resolution": {
            "Height": 1080,
            "Width": 1920
        },
        "Rate": 20254,
        "VmafScore": 95.807011
    },
    {
        "Resolution": {
            "Height": 1080,
            "Width": 1920
        },
        "Rate": 18818,
        "VmafScore": 95.578346
    },
    {
        "Resolution": {
            "Height": 1080,
            "Width": 1920
        },
        "Rate": 17382,
        "VmafScore": 95.34212
    },
    {
        "Resolution": {
            "Height": 1080,
            "Width": 1920
        },
        "Rate": 15946,
        "VmafScore": 95.039827
    },
    {
        "Resolution": {
            "Height": 1080,
            "Width": 1920
        },
        "Rate": 14510,
        "VmafScore": 94.693253
    },
    {
        "Resolution": {
            "Height": 1080,
            "Width": 1920
        },
        "Rate": 13074,
        "VmafScore": 94.220602
    },
    {
        "Resolution": {
            "Height": 1080,
            "Width": 1920
        },
        "Rate": 11638,
        "VmafScore": 93.699653
    },
    {
        "Resolution": {
            "Height": 1080,
            "Width": 1920
        },
        "Rate": 10202,
        "VmafScore": 92.99052
    },
    {
        "Resolution": {
            "Height": 1080,
            "Width": 1920
        },
        "Rate": 8766,
        "VmafScore": 92.020667
    },
    {
        "Resolution": {
            "Height": 1080,
            "Width": 1920
        },
        "Rate": 7330,
        "VmafScore": 90.718835
    },
    {
        "Resolution": {
            "Height": 1080,
            "Width": 1920
        },
        "Rate": 5894,
        "VmafScore": 89.011849
    },
    {
        "Resolution": {
            "Height": 720,
            "Width": 1280
        },
        "Rate": 4458,
        "VmafScore": 87.102693
    },
    {
        "Resolution": {
            "Height": 720,
            "Width": 1280
        },
        "Rate": 3022,
        "VmafScore": 84.148897
    },
    {
        "Resolution": {
            "Height": 540,
            "Width": 960
        },
        "Rate": 1586,
        "VmafScore": 78.446795
    },
    {
        "Resolution": {
            "Height": 360,
            "Width": 640
        },
        "Rate": 150,
        "VmafScore": 41.373812
    }
]
