[
    {
        "Resolution": {
            "Height": 720,
            "Width": 1280
        },
        "Rate": 19378,
        "VmafScore": 99.358245
    },
    {
        "Resolution": {
            "Height": 720,
            "Width": 1280
        },
        "Rate": 18366,
        "VmafScore": 99.322991
    },
    {
        "Resolution": {
            "Height": 720,
            "Width": 1280
        },
        "Rate": 17354,
        "VmafScore": 99.281727
    },
    {
        "Resolution": {
            "Height": 720,
            "Width": 1280
        },
        "Rate": 16342,
        "VmafScore": 99.236151
    },
    {
        "Resolution": {
            "Height": 720,
            "Width": 1280
        },
        "Rate": 15330,
        "VmafScore": 99.179568
    },
    {
        "Resolution": {
            "Height": 720,
            "Width": 1280
        },
        "Rate": 14318,
        "VmafScore": 99.111849
    },
    {
        "Resolution": {
            "Height": 720,
            "Width": 1280
        },
        "Rate": 13306,
        "VmafScore": 99.021201
    },
    {
        "Resolution": {
            "Height": 720,
            "Width": 1280
        },
        "Rate": 12294,
        "VmafScore": 98.90981
    },
    {
        "Resolution": {
            "Height": 720,
            "Width": 1280
        },
        "Rate": 11282,
        "VmafScore": 98.76287
    },
    {
        "Resolution": {
            "Height": 720,
            "Width": 1280
        },
        "Rate": 10270,
        "VmafScore": 98.598605
    },
    {
        "Resolution": {
            "Height": 720,
            "Width": 1280
        },
        "Rate": 9258,
        "VmafScore": 98.383527
    },
    {
        "Resolution": {
            "Height": 720,
            "Width": 1280
        },
        "Rate": 8246,
        "VmafScore": 98.092594
    },
    {
        "Resolution": {
            "Height": 720,
            "Width": 1280
        },
        "Rate": 7234,
        "VmafScore": 97.67591
    },
    {
        "Resolution": {
            "Height": 720,
            "Width": 1280
        },
        "Rate": 6222,
        "VmafScore": 97.029294
    },
    {
        "Resolution": {
            "Height": 540,
            "Width": 960
        },
        "Rate": 5210,
        "VmafScore": 96.313068
    },
    {
        "Resolution": {
            "Height": 540,
            "Width": 960
        },
        "Rate": 4198,
        "VmafScore": 95.316225
    },
    {
        "Resolution": {
            "Height": 540,
            "Width": 960
        },
        "Rate": 3186,
        "VmafScore": 93.626524
    },
    {
        "Resolution": {
            "Height": 360,
            "Width": 640
        },
        "Rate": 2174,
        "VmafScore": 90.882939
    },
    {
        "Resolution": {
            "Height": 360,
            "Width": 640
        },
        "Rate": 1162,
        "VmafScore": 84.136843
    },
    {
        "Resolution": {
            "Height": 270,
            "Width": 480
        },
        "Rate": 150,
        "VmafScore": 39.09977
    }
]
