[
    {
        "Resolution": {
            "Height": 1080,
            "Width": 1920
        },
        "Rate": 10000,
        "VmafScore": 95.591597
    },
    {
        "Resolution": {
            "Height": 1080,
            "Width": 1920
        },
        "Rate": 9500,
        "VmafScore": 95.461731
    },
    {
        "Resolution": {
            "Height": 1080,
            "Width": 1920
        },
        "Rate": 9000,
        "VmafScore": 95.334613
    },
    {
        "Resolution": {
            "Height": 1080,
            "Width": 1920
        },
        "Rate": 8500,
        "VmafScore": 95.199648
    },
    {
        "Resolution": {
            "Height": 1080,
            "Width": 1920
        },
        "Rate": 8000,
        "VmafScore": 95.016403
    },
    {
        "Resolution": {
            "Height": 1080,
            "Width": 1920
        },
        "Rate": 7500,
        "VmafScore": 94.834422
    },
    {
        "Resolution": {
            "Height": 1080,
            "Width": 1920
        },
        "Rate": 7000,
        "VmafScore": 94.63695
    },
    {
        "Resolution": {
            "Height": 1080,
            "Width": 1920
        },
        "Rate": 6500,
        "VmafScore": 94.387714
    },
    {
        "Resolution": {
            "Height": 1080,
            "Width": 1920
        },
        "Rate": 6000,
        "VmafScore": 94.086581
    },
    {
        "Resolution": {
            "Height": 1080,
            "Width": 1920
        },
        "Rate": 5500,
        "VmafScore": 93.75331
    },
    {
        "Resolution": {
            "Height": 1080,
            "Width": 1920
        },
        "Rate": 5000,
        "VmafScore": 93.326232
    },
    {
        "Resolution": {
            "Height": 1080,
            "Width": 1920
        },
        "Rate": 4500,
        "VmafScore": 92.83674
    },
    {
        "Resolution": {
            "Height": 1080,
            "Width": 1920
        },
        "Rate": 4000,
        "VmafScore": 92.159016
    },
    {
        "Resolution": {
            "Height": 1080,
            "Width": 1920
        },
        "Rate": 3500,
        "VmafScore": 91.416606
    },
    {
        "Resolution": {
            "Height": 1080,
            "Width": 1920
        },
        "Rate": 3000,
        "VmafScore": 90.397827
    },
    {
        "Resolution": {
            "Height": 1080,
            "Width": 1920
        },
        "Rate": 2500,
        "VmafScore": 88.990796
    },
    {
        "Resolution": {
            "Height": 1080,
            "Width": 1920
        },
        "Rate": 2000,
        "VmafScore": 86.784406
    },
    {
        "Resolution": {
            "Height": 1080,
            "Width": 1920
        },
        "Rate": 1500,
        "VmafScore": 83.659879
    },
    {
        "Resolution": {
            "Height": 1080,
            "Width": 1920
        },
        "Rate": 1000,
        "VmafScore": 78.304446
    },
    {
        "Resolution": {
            "Height": 720,
            "Width": 1280
        },
        "Rate": 500,
        "VmafScore": 67.237473
    }
]
