[
    {
        "Resolution": {
            "Height": 720,
            "Width": 1280
        },
        "Rate": 5000,
        "VmafScore": 98.159356
    },
    {
        "Resolution": {
            "Height": 720,
            "Width": 1280
        },
        "Rate": 4500,
        "VmafScore": 98.116458
    },
    {
        "Resolution": {
            "Height": 720,
            "Width": 1280
        },
        "Rate": 4000,
        "VmafScore": 98.024564
    },
    {
        "Resolution": {
            "Height": 720,
            "Width": 1280
        },
        "Rate": 3500,
        "VmafScore": 97.903143
    },
    {
        "Resolution": {
            "Height": 720,
            "Width": 1280
        },
        "Rate": 3000,
        "VmafScore": 97.696316
    },
    {
        "Resolution": {
            "Height": 720,
            "Width": 1280
        },
        "Rate": 2500,
        "VmafScore": 97.415576
    },
    {
        "Resolution": {
            "Height": 720,
            "Width": 1280
        },
        "Rate": 2000,
        "VmafScore": 97.000811
    },
    {
        "Resolution": {
            "Height": 720,
            "Width": 1280
        },
        "Rate": 1500,
        "VmafScore": 96.360672
    },
    {
        "Resolution": {
            "Height": 720,
            "Width": 1280
        },
        "Rate": 1000,
        "VmafScore": 95.105663
    },
    {
        "Resolution": {
            "Height": 720,
            "Width": 1280
        },
        "Rate": 500,
        "VmafScore": 91.494546
    }
]
