[
    {
        "Resolution": {
            "Height": 720,
            "Width": 1280
        },
        "Rate": 2500,
        "VmafScore": 97.239497
    },
    {
        "Resolution": {
            "Height": 720,
            "Width": 1280
        },
        "Rate": 2000,
        "VmafScore": 97.044697
    },
    {
        "Resolution": {
            "Height": 720,
            "Width": 1280
        },
        "Rate": 1500,
        "VmafScore": 96.665256
    },
    {
        "Resolution": {
            "Height": 720,
            "Width": 1280
        },
        "Rate": 1000,
        "VmafScore": 95.323273
    },
    {
        "Resolution": {
            "Height": 720,
            "Width": 1280
        },
        "Rate": 500,
        "VmafScore": 90.074634
    }
]
