[
    {
        "Resolution": {
            "Height": 720,
            "Width": 1280
        },
        "Rate": 10000,
        "VmafScore": 98.130153
    },
    {
        "Resolution": {
            "Height": 720,
            "Width": 1280
        },
        "Rate": 9500,
        "VmafScore": 98.06359
    },
    {
        "Resolution": {
            "Height": 720,
            "Width": 1280
        },
        "Rate": 9000,
        "VmafScore": 97.98831
    },
    {
        "Resolution": {
            "Height": 720,
            "Width": 1280
        },
        "Rate": 8500,
        "VmafScore": 97.904431
    },
    {
        "Resolution": {
            "Height": 720,
            "Width": 1280
        },
        "Rate": 8000,
        "VmafScore": 97.809589
    },
    {
        "Resolution": {
            "Height": 720,
            "Width": 1280
        },
        "Rate": 7500,
        "VmafScore": 97.700176
    },
    {
        "Resolution": {
            "Height": 720,
            "Width": 1280
        },
        "Rate": 7000,
        "VmafScore": 97.573952
    },
    {
        "Resolution": {
            "Height": 720,
            "Width": 1280
        },
        "Rate": 6500,
        "VmafScore": 97.441193
    },
    {
        "Resolution": {
            "Height": 720,
            "Width": 1280
        },
        "Rate": 6000,
        "VmafScore": 97.281082
    },
    {
        "Resolution": {
            "Height": 720,
            "Width": 1280
        },
        "Rate": 5500,
        "VmafScore": 97.104541
    },
    {
        "Resolution": {
            "Height": 720,
            "Width": 1280
        },
        "Rate": 5000,
        "VmafScore": 96.873656
    },
    {
        "Resolution": {
            "Height": 720,
            "Width": 1280
        },
        "Rate": 4500,
        "VmafScore": 96.598058
    },
    {
        "Resolution": {
            "Height": 720,
            "Width": 1280
        },
        "Rate": 4000,
        "VmafScore": 96.264421
    },
    {
        "Resolution": {
            "Height": 720,
            "Width": 1280
        },
        "Rate": 3500,
        "VmafScore": 95.820709
    },
    {
        "Resolution": {
            "Height": 720,
            "Width": 1280
        },
        "Rate": 3000,
        "VmafScore": 95.247306
    },
    {
        "Resolution": {
            "Height": 720,
            "Width": 1280
        },
        "Rate": 2500,
        "VmafScore": 94.399209
    },
    {
        "Resolution": {
            "Height": 720,
            "Width": 1280
        },
        "Rate": 2000,
        "VmafScore": 93.051904
    },
    {
        "Resolution": {
            "Height": 720,
            "Width": 1280
        },
        "Rate": 1500,
        "VmafScore": 90.569059
    },
    {
        "Resolution": {
            "Height": 720,
            "Width": 1280
        },
        "Rate": 1000,
        "VmafScore": 85.418765
    },
    {
        "Resolution": {
            "Height": 540,
            "Width": 960
        },
        "Rate": 500,
        "VmafScore": 71.236664
    }
]
