[
    {
        "Resolution": {
            "Height": 1080,
            "Width": 1920
        },
        "Rate": 10000,
        "VmafScore": 69.969358
    },
    {
        "Resolution": {
            "Height": 1080,
            "Width": 1920
        },
        "Rate": 9500,
        "VmafScore": 69.154619
    },
    {
        "Resolution": {
            "Height": 720,
            "Width": 1280
        },
        "Rate": 9000,
        "VmafScore": 68.30883
    },
    {
        "Resolution": {
            "Height": 720,
            "Width": 1280
        },
        "Rate": 8500,
        "VmafScore": 67.540735
    },
    {
        "Resolution": {
            "Height": 720,
            "Width": 1280
        },
        "Rate": 8000,
        "VmafScore": 66.636152
    },
    {
        "Resolution": {
            "Height": 720,
            "Width": 1280
        },
        "Rate": 7500,
        "VmafScore": 65.774323
    },
    {
        "Resolution": {
            "Height": 720,
            "Width": 1280
        },
        "Rate": 7000,
        "VmafScore": 64.839233
    },
    {
        "Resolution": {
            "Height": 720,
            "Width": 1280
        },
        "Rate": 6500,
        "VmafScore": 63.829126
    },
    {
        "Resolution": {
            "Height": 720,
            "Width": 1280
        },
        "Rate": 6000,
        "VmafScore": 62.849745
    },
    {
        "Resolution": {
            "Height": 720,
            "Width": 1280
        },
        "Rate": 5500,
        "VmafScore": 61.785741
    },
    {
        "Resolution": {
            "Height": 720,
            "Width": 1280
        },
        "Rate": 5000,
        "VmafScore": 60.569729
    },
    {
        "Resolution": {
            "Height": 720,
            "Width": 1280
        },
        "Rate": 4500,
        "VmafScore": 59.292974
    },
    {
        "Resolution": {
            "Height": 720,
            "Width": 1280
        },
        "Rate": 4000,
        "VmafScore": 57.903806
    },
    {
        "Resolution": {
            "Height": 720,
            "Width": 1280
        },
        "Rate": 3500,
        "VmafScore": 56.342224
    },
    {
        "Resolution": {
            "Height": 720,
            "Width": 1280
        },
        "Rate": 3000,
        "VmafScore": 54.604406
    },
    {
        "Resolution": {
            "Height": 720,
            "Width": 1280
        },
        "Rate": 2500,
        "VmafScore": 52.60742
    },
    {
        "Resolution": {
            "Height": 720,
            "Width": 1280
        },
        "Rate": 2000,
        "VmafScore": 50.15894
    },
    {
        "Resolution": {
            "Height": 720,
            "Width": 1280
        },
        "Rate": 1500,
        "VmafScore": 46.799394
    },
    {
        "Resolution": {
            "Height": 720,
            "Width": 1280
        },
        "Rate": 1000,
        "VmafScore": 41.692356
    },
    {
        "Resolution": {
            "Height": 540,
            "Width": 960
        },
        "Rate": 500,
        "VmafScore": 32.276134
    }
]
